seaduck/__init__.py
seaduck/eulerian.py
seaduck/eulerian_budget.py
seaduck/get_masks.py
seaduck/kernel_weight.py
seaduck/lagrangian.py
seaduck/lagrangian_budget.py
seaduck/ocedata.py
seaduck/oceinterp.py
seaduck/runtime_conf.py
seaduck/smart_read.py
seaduck/topology.py
seaduck/utils.py
seaduck/version.py
seaduck-1.0.3.dist-info/licenses/LICENSE
seaduck-1.0.3.dist-info/METADATA
seaduck-1.0.3.dist-info/WHEEL
seaduck-1.0.3.dist-info/top_level.txt
seaduck-1.0.3.dist-info/RECORD
